cost_katana/__init__.py
cost_katana/cli.py
cost_katana/client.py
cost_katana/config.py
cost_katana/exceptions.py
cost_katana/models.py
cost_katana/models_constants.py
cost_katana/logging/__init__.py
cost_katana/logging/ai_logger.py
cost_katana/logging/logger.py
cost_katana/templates/__init__.py
cost_katana/templates/template_manager.py
cost_katana-2.2.6.dist-info/licenses/LICENSE
cost_katana-2.2.6.dist-info/METADATA
cost_katana-2.2.6.dist-info/WHEEL
cost_katana-2.2.6.dist-info/entry_points.txt
cost_katana-2.2.6.dist-info/top_level.txt
cost_katana-2.2.6.dist-info/RECORD
