Metadata-Version: 2.4
Name: cost-katana
Version: 2.2.6
Summary: The simplest way to use AI in Python with automatic cost tracking and optimization
Home-page: https://github.com/Hypothesize-Tech/cost-katana-python
Author: Cost Katana Team
Author-email: support@costkatana.com
Project-URL: Bug Reports, https://github.com/Hypothesize-Tech/cost-katana-python/issues
Project-URL: Source, https://github.com/Hypothesize-Tech/cost-katana-python
Project-URL: Documentation, https://docs.costkatana.com
Keywords: ai,machine learning,cost optimization,openai,anthropic,aws bedrock,gemini,claude
Classifier: Development Status :: 4 - Beta
Classifier: Intended Audience :: Developers
Classifier: License :: OSI Approved :: MIT License
Classifier: Operating System :: OS Independent
Classifier: Programming Language :: Python :: 3
Classifier: Programming Language :: Python :: 3.8
Classifier: Programming Language :: Python :: 3.9
Classifier: Programming Language :: Python :: 3.10
Classifier: Programming Language :: Python :: 3.11
Classifier: Programming Language :: Python :: 3.12
Classifier: Topic :: Software Development :: Libraries :: Python Modules
Classifier: Topic :: Scientific/Engineering :: Artificial Intelligence
Requires-Python: >=3.8
License-File: LICENSE
Requires-Dist: requests>=2.28.0
Requires-Dist: httpx>=0.24.0
Requires-Dist: typing-extensions>=4.0.0
Requires-Dist: pydantic>=2.0.0
Requires-Dist: python-dotenv>=0.19.0
Requires-Dist: rich>=12.0.0
Dynamic: author
Dynamic: author-email
Dynamic: classifier
Dynamic: description
Dynamic: description-content-type
Dynamic: home-page
Dynamic: keywords
Dynamic: license-file
Dynamic: project-url
Dynamic: requires-dist
Dynamic: requires-python
Dynamic: summary
